foundational/__init__.py
foundational/attrdict.py
foundational/binary.py
foundational/casing.py
foundational/client.py
foundational/collections.py
foundational/dates.py
foundational/download.py
foundational/encoding.py
foundational/enum.py
foundational/exceptions.py
foundational/files.py
foundational/floats.py
foundational/functions.py
foundational/getter.py
foundational/guids.py
foundational/hashing.py
foundational/http.py
foundational/inflections.py
foundational/inheritance.py
foundational/ips.py
foundational/iterables.py
foundational/memory.py
foundational/mixins.py
foundational/nesting.py
foundational/nulls.py
foundational/properties.py
foundational/sets.py
foundational/sizes.py
foundational/submodules.py
foundational/time_periods.py
foundational/timezone.py
foundational/tracebacks.py
foundational/zip_archive.py
foundational-0.4.5.dist-info/METADATA
foundational-0.4.5.dist-info/WHEEL
foundational-0.4.5.dist-info/licenses/LICENSE
foundational-0.4.5.dist-info/RECORD
