Metadata-Version: 2.3
Name: foundational
Version: 0.4.5
Summary: A little library for commonly used Python functions
Project-URL: Homepage, https://github.com/goodcleanfun/foundational
Project-URL: Repository, https://github.com/goodcleanfun/foundational
Author: Al Barrentine
License-Expression: MIT
License-File: LICENSE
Keywords: foundational,utils
Classifier: Intended Audience :: Developers
Classifier: License :: OSI Approved :: MIT License
Classifier: Natural Language :: English
Classifier: Programming Language :: Python :: 3
Classifier: Programming Language :: Python :: 3.8
Classifier: Programming Language :: Python :: 3.9
Classifier: Programming Language :: Python :: 3.10
Classifier: Programming Language :: Python :: 3.11
Classifier: Programming Language :: Python :: 3.12
Requires-Python: >=3.8
Requires-Dist: chardet
Requires-Dist: fsspec>=2022.3.0
Requires-Dist: ftfy
Requires-Dist: furl
Requires-Dist: inflect
Requires-Dist: pendulum
Requires-Dist: python-dateutil
Requires-Dist: pytz>=2022.1
Requires-Dist: requests
Requires-Dist: url-normalize
Requires-Dist: user-agents
